flexsm/__init__.py
flexsm-0.1.0.0.dist-info/METADATA
flexsm-0.1.0.0.dist-info/RECORD
flexsm-0.1.0.0.dist-info/WHEEL
flexsm-0.1.0.0.dist-info/top_level.txt
